{
  "title": "ROOT",
  "subnav": [
    {
      "title": "Home",
      "altTitle": "Why use gutter-grid?",
      "link": "/",
      "template": "home",
      "subNavigable": false
    },
    {
      "title": "Installation"
    },
    {
    	"title": "How to support legacy browsers"
    },
    {
      "title": "Basic usage"
    },
    {
      "title": "Using columns"
    },
    {
      "title": "Enabling/disabling wrapping"
    },
    {
    	"title" : "Cells that span multiple columns"
    },
    {
      "title": "Adding Gutters"
    },
    {
    	"title": "Outter gutters"
    },
    {
    	"title": "Nesting grids"
    },
    {
    	"title": "Borders and shadows on guttered cells"
    },
    {
    	"title": "Horizontal cell alignments"
    },
    {
    	"title": "Vertical cell alignments"
    },
    {
    	"title": "Controlling cell growth and shrinkage"
    }
  ]
}
